aienlarge/__init__.py
aienlarge/aienlarger.py
aienlarge_py-0.1.2.dist-info/licenses/LICENSE
aienlarge_py-0.1.2.dist-info/METADATA
aienlarge_py-0.1.2.dist-info/WHEEL
aienlarge_py-0.1.2.dist-info/top_level.txt
aienlarge_py-0.1.2.dist-info/RECORD
