Metadata-Version: 2.4
Name: aienlarge-py
Version: 0.1.2
Summary: An asynchronous Python API wrapper for AI Enlarger image enhancement service
Home-page: https://github.com/SSL-ACTX/aienlarger-py
Author: SSL-ACTX
Author-email: seuriin@gmail.com
License: MIT
Classifier: Programming Language :: Python :: 3
Classifier: License :: OSI Approved :: MIT License
Classifier: Operating System :: OS Independent
Requires-Python: >=3.7
License-File: LICENSE
Requires-Dist: httpx
Dynamic: license-file
